MetaboConverter/__init__.py
MetaboConverter/analysis.py
MetaboConverter/data_handling.py
MetaboConverter/gui_widgets.py
MetaboConverter/main.py
MetaboConverter-1.0.3.dist-info/METADATA
MetaboConverter-1.0.3.dist-info/WHEEL
MetaboConverter-1.0.3.dist-info/top_level.txt
MetaboConverter-1.0.3.dist-info/RECORD
